[
  {
    "availableCopies": 10,
    "id": 1,
    "title": "C++ ho ho",
    "subject": {
      "id": 4,
      "title": "C++"
    },
    "author": {
      "id": 2,
      "title": "Rajesh",
      "contact": "2562"
    },
    "publisher": {
      "id": 3,
      "title": "Mero Publication",
      "contact": "455225"
    },
    "edition": "2010",
    "isbn": "2256fs",
    "shelfNo": {
      "id": 2,
      "location": "B7"
    },
    "numberOfCopy": 10
  },
  {
    "availableCopies": 5,
    "id": 2,
    "title": "Java Programming",
    "subject": {
      "id": 1,
      "title": "Java"
    },
    "author": {
      "id": 1,
      "title": "Sujan",
      "contact": "2562"
    },
    "publisher": {
      "id": 3,
      "title": "Lala Publication",
      "contact": "455225"
    },
    "edition": "2010",
    "isbn": "2256fs",
    "shelfNo": {
      "id": 2,
      "location": "B7"
    },
    "numberOfCopy": 5
  },
  {
    "availableCopies": 5,
    "id": 8601,
    "title": "Java for Dummies",
    "subject": {
      "id": 1,
      "title": "Java"
    },
    "author": {
      "id": 4,
      "title": "Xi Jinping",
      "contact": "236952"
    },
    "publisher": {
      "id": 4,
      "title": "Himalayan Publication",
      "contact": "4935562"
    },
    "edition": "2008",
    "isbn": "nnlo52s556",
    "shelfNo": {
      "id": 2,
      "location": "B2-C"
    },
    "numberOfCopy": 0
  }
]